{
  "manual": {
    "checks": {
      "1.4.4": "tbd",
      "1.4.10": "tbd",
      "1.4.12": "tbd",
      "2.1.1+2.1.2": "tbd",
      "2.4.3": "tbd",
      "2.4.6": "tbd",
      "2.4.7": "tbd"
    }
  },
  "automatic": [
    {
      "wcag_id": [
        "Principle1.Guideline1_3.1_3_1.H42.2",
        "Principle1.Guideline1_3.1_3_1.G141"
      ],
      "url": [
        "https://dequeuniversity.com/rules/axe/4.10/page-has-heading-one",
        "https://dequeuniversity.com/rules/axe/4.10/heading-order",
        "https://dequeuniversity.com/rules/axe/4.10/empty-heading"
      ],
      "impact": "moderate",
      "name": "Headings; Wrong Order, Empty & Missing Headings;",
      "amount_nodes_failed": 1,
      "issues": [
        {
          "id": "https://dequeuniversity.com/rules/axe/4.10/heading-order",
          "source": "axe-core",
          "title": "Heading levels should only increase by one",
          "description": "Ensure the order of headings is semantically correct",
          "impact": "moderate",
          "nodes": {
            "any": [
              {
                "id": "heading-order",
                "data": null,
                "relatedNodes": [],
                "impact": "moderate",
                "message": "Heading order invalid"
              }
            ],
            "all": [],
            "none": [],
            "impact": "moderate",
            "html": "<h3>Fast Delivery</h3>",
            "target": [
              ".feature:nth-child(1) > h3"
            ],
            "failureSummary": "Fix any of the following:\n  Heading order invalid"
          }
        }
      ]
    },
    {
      "wcag_id": "Principle2.Guideline2_4.2_4_1.G1,G123,G124.NoSuchID",
      "url": null,
      "impact": "tbd",
      "name": "tbd",
      "amount_nodes_failed": 6,
      "issues": [
        {
          "id": "Principle2.Guideline2_4.2_4_1.G1,G123,G124.NoSuchID",
          "source": "pa11y",
          "title": "This link points to a named anchor \"home\" within the document, but no anchor exists with that name.",
          "description": "<a href=\"#home\">Home</a>",
          "impact": "error",
          "original_issue": {
            "code": "WCAG2AA.Principle2.Guideline2_4.2_4_1.G1,G123,G124.NoSuchID",
            "type": "error",
            "typeCode": 1,
            "message": "This link points to a named anchor \"home\" within the document, but no anchor exists with that name.",
            "context": "<a href=\"#home\">Home</a>",
            "selector": "html > body > header > nav > ul > li:nth-child(1) > a",
            "runner": "htmlcs",
            "runnerExtras": {}
          }
        },
        {
          "id": "Principle2.Guideline2_4.2_4_1.G1,G123,G124.NoSuchID",
          "source": "pa11y",
          "title": "This link points to a named anchor \"about\" within the document, but no anchor exists with that name.",
          "description": "<a href=\"#about\">About</a>",
          "impact": "error",
          "original_issue": {
            "code": "WCAG2AA.Principle2.Guideline2_4.2_4_1.G1,G123,G124.NoSuchID",
            "type": "error",
            "typeCode": 1,
            "message": "This link points to a named anchor \"about\" within the document, but no anchor exists with that name.",
            "context": "<a href=\"#about\">About</a>",
            "selector": "html > body > header > nav > ul > li:nth-child(2) > a",
            "runner": "htmlcs",
            "runnerExtras": {}
          }
        },
        {
          "id": "Principle2.Guideline2_4.2_4_1.G1,G123,G124.NoSuchID",
          "source": "pa11y",
          "title": "This link points to a named anchor \"contact\" within the document, but no anchor exists with that name.",
          "description": "<a href=\"#contact\">Contact</a>",
          "impact": "error",
          "original_issue": {
            "code": "WCAG2AA.Principle2.Guideline2_4.2_4_1.G1,G123,G124.NoSuchID",
            "type": "error",
            "typeCode": 1,
            "message": "This link points to a named anchor \"contact\" within the document, but no anchor exists with that name.",
            "context": "<a href=\"#contact\">Contact</a>",
            "selector": "html > body > header > nav > ul > li:nth-child(3) > a",
            "runner": "htmlcs",
            "runnerExtras": {}
          }
        },
        {
          "id": "Principle2.Guideline2_4.2_4_1.G1,G123,G124.NoSuchID",
          "source": "pa11y",
          "title": "This link points to a named anchor \"home\" within the document, but no anchor exists with that name.",
          "description": "<a href=\"#home\">Home</a>",
          "impact": "error",
          "original_issue": {
            "code": "WCAG2AA.Principle2.Guideline2_4.2_4_1.G1,G123,G124.NoSuchID",
            "type": "error",
            "typeCode": 1,
            "message": "This link points to a named anchor \"home\" within the document, but no anchor exists with that name.",
            "context": "<a href=\"#home\">Home</a>",
            "selector": "html > body > main > footer > nav > ul > li:nth-child(1) > a",
            "runner": "htmlcs",
            "runnerExtras": {}
          }
        },
        {
          "id": "Principle2.Guideline2_4.2_4_1.G1,G123,G124.NoSuchID",
          "source": "pa11y",
          "title": "This link points to a named anchor \"about\" within the document, but no anchor exists with that name.",
          "description": "<a href=\"#about\">About</a>",
          "impact": "error",
          "original_issue": {
            "code": "WCAG2AA.Principle2.Guideline2_4.2_4_1.G1,G123,G124.NoSuchID",
            "type": "error",
            "typeCode": 1,
            "message": "This link points to a named anchor \"about\" within the document, but no anchor exists with that name.",
            "context": "<a href=\"#about\">About</a>",
            "selector": "html > body > main > footer > nav > ul > li:nth-child(2) > a",
            "runner": "htmlcs",
            "runnerExtras": {}
          }
        },
        {
          "id": "Principle2.Guideline2_4.2_4_1.G1,G123,G124.NoSuchID",
          "source": "pa11y",
          "title": "This link points to a named anchor \"contact\" within the document, but no anchor exists with that name.",
          "description": "<a href=\"#contact\">Contact</a>",
          "impact": "error",
          "original_issue": {
            "code": "WCAG2AA.Principle2.Guideline2_4.2_4_1.G1,G123,G124.NoSuchID",
            "type": "error",
            "typeCode": 1,
            "message": "This link points to a named anchor \"contact\" within the document, but no anchor exists with that name.",
            "context": "<a href=\"#contact\">Contact</a>",
            "selector": "html > body > main > footer > nav > ul > li:nth-child(3) > a",
            "runner": "htmlcs",
            "runnerExtras": {}
          }
        }
      ]
    }
  ]
}